binsolver/__init__.py
binsolver/client.py
binsolver/models.py
binsolver-1.0.1.dist-info/METADATA
binsolver-1.0.1.dist-info/WHEEL
binsolver-1.0.1.dist-info/RECORD
