Metadata-Version: 2.4
Name: binsolver
Version: 1.0.1
Summary: Official Python SDK for the BinSolver API
Project-URL: Homepage, https://binsolver.com
Project-URL: Repository, https://github.com/binsolver/binsolver-py
Project-URL: Documentation, https://binsolver.com/docs
Author-email: BinSolver Team <hello@binsolver.com>
License-Expression: MIT
Keywords: 3d packing,api,bin packing,logistics,optimization
Classifier: Development Status :: 4 - Beta
Classifier: Intended Audience :: Developers
Classifier: License :: OSI Approved :: MIT License
Classifier: Programming Language :: Python :: 3
Classifier: Programming Language :: Python :: 3.8
Classifier: Programming Language :: Python :: 3.9
Classifier: Programming Language :: Python :: 3.10
Classifier: Programming Language :: Python :: 3.11
Classifier: Programming Language :: Python :: 3.12
Requires-Python: >=3.8
Requires-Dist: httpx>=0.25.0
Requires-Dist: pydantic>=2.0.0
